nexus_streamer/__init__.py
nexus_streamer/application_logger.py
nexus_streamer/convert_units.py
nexus_streamer/create_data_sources_from_nexus.py
nexus_streamer/data_source.py
nexus_streamer/event_data_source.py
nexus_streamer/generate_json_description.py
nexus_streamer/isis_data_source.py
nexus_streamer/kafka_producer.py
nexus_streamer/launch_nexus_streamer.py
nexus_streamer/log_data_source.py
nexus_streamer/parse_commandline_args.py
nexus_streamer/publish_run_message.py
nexus_streamer/read_detector_spectrum_map_file.py
nexus_streamer/source_error.py
nexus_streamer/source_to_stream.py
nexus_streamer-0.2.1.dist-info/LICENSE
nexus_streamer-0.2.1.dist-info/METADATA
nexus_streamer-0.2.1.dist-info/WHEEL
nexus_streamer-0.2.1.dist-info/entry_points.txt
nexus_streamer-0.2.1.dist-info/top_level.txt
nexus_streamer-0.2.1.dist-info/RECORD
