Metadata-Version: 2.1
Name: nexus-streamer
Version: 0.2.1
Summary: UNKNOWN
Home-page: https://github.com/ess-dmsc/nexus-streamer-python
Author: European Spallation Source - Data Management and Software Centre
License: BSD 2-clause
Platform: any
Requires-Dist: configargparse
Requires-Dist: confluent-kafka
Requires-Dist: ess-streaming-data-types
Requires-Dist: h5py
Requires-Dist: numpy
Requires-Dist: graypy
Requires-Dist: pint
Requires-Dist: nexusformat
Requires-Dist: py-dateutil
Requires-Dist: ipython
